{
  "name": "stock_ntdoy_global_quote",
  "type": "stock_quote",
  "url": "https://www.alphavantage.co/documentation/#latestprice",
  "checkedAt": "2025-09-18T20:55:39.853Z",
  "data": {
    "symbol": "NTDOY",
    "source": "alphavantage",
    "price": 22.72,
    "change": -0.83,
    "changePercent": -3.5244,
    "raw": {
      "01. symbol": "NTDOY",
      "02. open": "23.2000",
      "03. high": "23.2000",
      "04. low": "22.4500",
      "05. price": "22.7200",
      "06. volume": "1382648",
      "07. latest trading day": "2025-09-17",
      "08. previous close": "23.5500",
      "09. change": "-0.8300",
      "10. change percent": "-3.5244%"
    }
  }
}
